framed/__init__.py
framed/bioreactor/__init__.py
framed/bioreactor/base.py
framed/bioreactor/bioreactors.py
framed/bioreactor/dfba.py
framed/bioreactor/dyssco.py
framed/cobra/__init__.py
framed/cobra/deletion.py
framed/cobra/ensemble.py
framed/cobra/essentiality.py
framed/cobra/genewise.py
framed/cobra/phaseplane.py
framed/cobra/plotting.py
framed/cobra/reconstruction.py
framed/cobra/simulation.py
framed/cobra/strain_design.py
framed/cobra/thermodynamics.py
framed/cobra/variability.py
framed/community/__init__.py
framed/community/model.py
framed/experimental/__init__.py
framed/experimental/benchmark.py
framed/experimental/elements.py
framed/experimental/fluxutils.py
framed/experimental/marge.py
framed/experimental/mass_conservation.py
framed/experimental/medium.py
framed/experimental/metanetx.py
framed/experimental/reduction.py
framed/experimental/sampling.py
framed/experimental/visualization/KEGG.py
framed/experimental/visualization/__init__.py
framed/experimental/visualization/escher_maps.py
framed/experimental/visualization/iPATH.py
framed/io/__init__.py
framed/io/bioopt.py
framed/io/cache.py
framed/io/plaintext.py
framed/io/sbml.py
framed/kinetic/__init__.py
framed/kinetic/fitting.py
framed/kinetic/plotting.py
framed/kinetic/sampling.py
framed/kinetic/simulation.py
framed/model/__init__.py
framed/model/cbmodel.py
framed/model/environment.py
framed/model/fixes.py
framed/model/model.py
framed/model/odemodel.py
framed/model/parser.py
framed/model/transformation.py
framed/omics/__init__.py
framed/omics/dataset.py
framed/omics/simulation.py
framed/solvers/__init__.py
framed/solvers/cplex_interface.py
framed/solvers/gurobi_interface.py
framed/solvers/solver.py
framed/unittests/__init__.py
framed/unittests/kinetic.py
framed/unittests/tests_cobra.py
framed/unittests/tests_sbml.py
framed-0.5.2.data/scripts/framed-deletions
framed-0.5.2.dist-info/LICENSE
framed-0.5.2.dist-info/METADATA
framed-0.5.2.dist-info/WHEEL
framed-0.5.2.dist-info/top_level.txt
framed-0.5.2.dist-info/RECORD
