Metadata-Version: 2.1
Name: framed
Version: 0.5.2
Summary: framed - metabolic modeling for python
Home-page: https://github.com/cdanielmachado/framed
Author: Daniel Machado
Author-email: cdanielmachado@gmail.com
License: Apache License Version 2.0
Keywords: metabolism modeling
Platform: UNKNOWN
Classifier: Development Status :: 4 - Beta
Classifier: Topic :: Scientific/Engineering :: Bio-Informatics
Classifier: Intended Audience :: Science/Research
Classifier: Programming Language :: Python :: 2.7
Classifier: License :: OSI Approved :: Apache Software License
Requires-Dist: numpy
Requires-Dist: scipy
Requires-Dist: sympy
Requires-Dist: python-libsbml
Requires-Dist: matplotlib
Requires-Dist: pandas
